invenio_records_editor/__init__.py
invenio_records_editor/config.py
invenio_records_editor/ext.py
invenio_records_editor/permissions.py
invenio_records_editor/version.py
invenio_records_editor/views.py
invenio_records_editor/static/mock-data/patches.json
invenio_records_editor/static/mock-data/problem-map.json
invenio_records_editor/static/mock-data/record.json
invenio_records_editor/static/mock-data/schema.json
invenio_records_editor/templates/invenio_records_editor/editor.html
invenio_records_editor/translations/messages.pot
invenio_records_editor/translations/en/LC_MESSAGES/messages.mo
invenio_records_editor/translations/en/LC_MESSAGES/messages.po
invenio_records_editor-1.0.0a3.dist-info/AUTHORS.rst
invenio_records_editor-1.0.0a3.dist-info/LICENSE
invenio_records_editor-1.0.0a3.dist-info/METADATA
invenio_records_editor-1.0.0a3.dist-info/WHEEL
invenio_records_editor-1.0.0a3.dist-info/entry_points.txt
invenio_records_editor-1.0.0a3.dist-info/top_level.txt
invenio_records_editor-1.0.0a3.dist-info/RECORD
